unicorner/__init__.py
unicorner/__main__.py
unicorner/cli.py
unicorner/dtos.py
unicorner/env.py
unicorner/extraction.py
unicorner/season_page.py
unicorner/values.py
unicorner-0.3.4.dist-info/LICENSE
unicorner-0.3.4.dist-info/METADATA
unicorner-0.3.4.dist-info/WHEEL
unicorner-0.3.4.dist-info/top_level.txt
unicorner-0.3.4.dist-info/RECORD
