Metadata-Version: 2.1
Name: unicorner
Version: 0.3.4
Summary: GM standings and fixtures parser
Home-page: https://github.com/zilupe/unicorner
Author: Jazeps Basko
Author-email: jazeps.basko@gmail.com
License: BSD license
Keywords: unicorner
Platform: UNKNOWN
Classifier: Development Status :: 2 - Pre-Alpha
Classifier: Intended Audience :: Developers
Classifier: License :: OSI Approved :: BSD License
Classifier: Natural Language :: English
Classifier: Programming Language :: Python :: 3
Classifier: Programming Language :: Python :: 3.7
Classifier: Programming Language :: Python :: 3.8
Requires-Python: >=3.7
Requires-Dist: aarghparse (==0.2.0)
Requires-Dist: cached-property
Requires-Dist: beautifulsoup4
Requires-Dist: requests
